cirqprojectq/__init__.py
cirqprojectq/_rules_pq_to_cirq.py
cirqprojectq/circ_engine.py
cirqprojectq/common_rules.py
cirqprojectq/common_rules_03x.py
cirqprojectq/common_rules_040.py
cirqprojectq/test_xmon_gates.py
cirqprojectq/xmon_decompositions.py
cirqprojectq/xmon_gates.py
cirqprojectq/xmon_gates_tests.py
cirqprojectq/xmon_rules.py
cirqprojectq/xmon_rules_03x.py
cirqprojectq/xmon_rules_040.py
cirqprojectq/xmon_setup.py
CirqProjectQ-0.2.3.dist-info/LICENSE
CirqProjectQ-0.2.3.dist-info/METADATA
CirqProjectQ-0.2.3.dist-info/WHEEL
CirqProjectQ-0.2.3.dist-info/top_level.txt
CirqProjectQ-0.2.3.dist-info/RECORD
