Metadata-Version: 2.1
Name: CirqProjectQ
Version: 0.2.3
Summary: PACKAGE NO LONGER ACTIVELY MAINTAINED Provides: ProjectQ decompositions from common gates to native cirq Xmon gates;  ProjectQ backend to convert a ProjectQ algorithm to a cirq.Circuit
Home-page: https://github.com/HQSquantumsimulations/CirqProjectQ
Author: HQS Quantum Simulations
Author-email: info@quantumsimulations.de
License: Apache License
Requires-Dist: cirq
Requires-Dist: projectq
Requires-Dist: numpy
Requires-Dist: pytest
